kobodata/__init__.py
kobodata-0.0.6.dist-info/METADATA
kobodata-0.0.6.dist-info/WHEEL
kobodata-0.0.6.dist-info/top_level.txt
kobodata-0.0.6.dist-info/RECORD
