Metadata-Version: 2.1
Name: kobodata
Version: 0.0.6
Summary: Python Tool for accessing online data from KOBO TOOLBOX.
Home-page: UNKNOWN
Author: Brightius Kalokola
Author-email: brightiuskalokola@gmail.com
License: MIT
Platform: UNKNOWN
Classifier: Programming Language :: Python :: 3
Classifier: License :: OSI Approved :: MIT License
Classifier: Operating System :: OS Independent
Requires-Dist: requests
